webhooksaas/__init__.py
webhooksaas/send_webhook/__init__.py
webhooksaas-0.0.1.dist-info/METADATA
webhooksaas-0.0.1.dist-info/WHEEL
webhooksaas-0.0.1.dist-info/top_level.txt
webhooksaas-0.0.1.dist-info/RECORD
